LICENSE
boardman/__init__.py
boardman/__main__.py
boardman/cli.py
boardman/cmd_collect.py
boardman/cmd_deploy.py
boardman/cmd_detect.py
boardman/cmd_get_mpy_compiler.py
boardman/cmd_mpy_compile.py
boardman/cmd_reset.py
boardman/config.py
boardman/constants.py
boardman/entities.py
boardman/tools.py
boardman-0.1.1.dist-info/LICENSE
boardman-0.1.1.dist-info/WHEEL
boardman-0.1.1.dist-info/entry_points.txt
boardman-0.1.1.dist-info/METADATA
boardman-0.1.1.dist-info/RECORD
